{
  "name": "@asaidimu/vite-autoload",
  "version": "1.0.0",
  "description": "Autoloader for vite",
  "main": "index.js",
  "types": "index.d.ts",
  "files": [
    "./*"
  ],
  "keywords": [
    "typescript"
  ],
  "author": "Saidimu <47994458+asaidimu@users.noreply.github.com>",
  "license": "MIT",
  "repository": {
    "type": "git",
    "url": "git+https://github.com/asaidimu/vite-autoload.git"
  },
  "bugs": {
    "url": "https://github.com/asaidimu/vite-autoload/issues"
  },
  "homepage": "https://github.com/asaidimu/vite-autoload#readme",
  "publishConfig": {
    "registry": "https://registry.npmjs.org/",
    "tag": "latest",
    "access": "public"
  },
  "dependencies": {},
  "devDependencies": {
    "@babel/parser": "^7.26.5",
    "@babel/traverse": "^7.26.5",
    "@babel/types": "^7.26.5",
    "@types/js-yaml": "^4.0.9",
    "@types/node": "^22.10.7",
    "@types/picomatch": "^4.0.0",
    "@typescript-eslint/eslint-plugin": "^5.57.0",
    "@typescript-eslint/parser": "^5.57.0",
    "chokidar": "^3.5.3",
    "es-module-lexer": "^1.6.0",
    "eslint": "^8.37.0",
    "js-yaml": "^4.1.0",
    "picomatch": "^4.0.2",
    "playwright": "^1.49.1",
    "tsup": "^7.0.0",
    "typescript": "~5.7.2",
    "vite": "^6.1.0",
    "zod": "^3.24.1"
  }
}
